setup.py
salesman/__init__.py
salesman/cmd_line.py
salesman.egg-info/PKG-INFO
salesman.egg-info/SOURCES.txt
salesman.egg-info/dependency_links.txt
salesman.egg-info/entry_points.txt
salesman.egg-info/requires.txt
salesman.egg-info/top_level.txt