Metadata-Version: 1.0
Name: salesman
Version: 0.0.1
Summary: Automatic Link Checker
Home-page: http://github.com/derferman/salesman/
Author: Kyle Conroy
Author-email: kyle.j.conroy@gmail.com
License: UNKNOWN
Keywords: http,checker
Platform: UNKNOWN
Classifier: Intended Audience :: Developers
Classifier: License :: OSI Approved :: MIT License
Classifier: Operating System :: OS Independent
Classifier: Programming Language :: Python
Classifier: Programming Language :: Python :: 2.7
Classifier: Topic :: Software Development :: Libraries :: Python Modules
